LICENSE
MANIFEST.in
README.rst
instax.py
setup.py
instax.egg-info/PKG-INFO
instax.egg-info/SOURCES.txt
instax.egg-info/dependency_links.txt
instax.egg-info/requires.txt
instax.egg-info/top_level.txt