Metadata-Version: 1.0
Name: instax
Version: 0.1.6
Summary: Making celery monitoring easier.
Home-page: https://github.com/cyberdelia/instax
Author: Timothee Peignier
Author-email: timothee.peignier@tryphon.org
License: Copyright (©) 2012 Timothée Peignier <timothee.peignier@tryphon.org>
